gempaterkini/__init__.py
earthquake_id_warning-0.0.2.dist-info/LICENSE
earthquake_id_warning-0.0.2.dist-info/METADATA
earthquake_id_warning-0.0.2.dist-info/WHEEL
earthquake_id_warning-0.0.2.dist-info/top_level.txt
earthquake_id_warning-0.0.2.dist-info/RECORD
