Metadata-Version: 2.1
Name: earthquake-id-warning
Version: 0.0.2
Summary: this project will report the latest earthquake in Indonesia from BMKG
Home-page: https://github.com/goestoremote/indonesia-earthquake
Author: Heru Setiawan
Author-email: lenterabots@gmail.com
Classifier: Programming Language :: Python :: 3
Classifier: License :: OSI Approved :: GNU General Public License v3 or later (GPLv3+)
Classifier: Operating System :: OS Independent
Classifier: Development Status :: 5 - Production/Stable
Requires-Python: >=3.6
License-File: LICENSE
